aws_control_tower_manifest_builder/__init__.py
aws_control_tower_manifest_builder/aws_control_tower_manifest_builder.py
aws_control_tower_manifest_builder/cli.py
aws_control_tower_manifest_builder/logger.py
aws_control_tower_manifest_builder/manifest-v2.schema.yaml
aws_control_tower_manifest_builder/manifest.yaml.j2
aws_control_tower_manifest_builder/manifest_input.py
aws_control_tower_manifest_builder-0.10.0.dist-info/AUTHORS.rst
aws_control_tower_manifest_builder-0.10.0.dist-info/LICENSE
aws_control_tower_manifest_builder-0.10.0.dist-info/METADATA
aws_control_tower_manifest_builder-0.10.0.dist-info/WHEEL
aws_control_tower_manifest_builder-0.10.0.dist-info/entry_points.txt
aws_control_tower_manifest_builder-0.10.0.dist-info/top_level.txt
aws_control_tower_manifest_builder-0.10.0.dist-info/RECORD
