Metadata-Version: 2.1
Name: aws-control-tower-manifest-builder
Version: 0.10.0
Summary: Python package to automatically build the AWS Control Tower Manifest given Cloud Formation templates as input.
Home-page: https://github.com/gabrielbac/aws_control_tower_manifest_builder
Author: Gabriel Bacallado
Author-email: gabriel.bacallado@gmail.com
License: MIT license
Keywords: aws_control_tower_manifest_builder
Platform: UNKNOWN
Classifier: Development Status :: 2 - Pre-Alpha
Classifier: Intended Audience :: Developers
Classifier: License :: OSI Approved :: MIT License
Classifier: Natural Language :: English
Classifier: Programming Language :: Python :: 3
Classifier: Programming Language :: Python :: 3.6
Classifier: Programming Language :: Python :: 3.7
Classifier: Programming Language :: Python :: 3.8
Requires-Python: >=3.6
License-File: LICENSE
License-File: AUTHORS.rst
Requires-Dist: ruamel.yaml ==0.17.20
Requires-Dist: prettytable ==3.0.0
Requires-Dist: Jinja2 ==3.1.3
